odoo10_addon_business_requirement_etherpad-10.0.1.0.0-py2.7-nspkg.pth
odoo/addons/business_requirement_etherpad/README.rst
odoo/addons/business_requirement_etherpad/__init__.py
odoo/addons/business_requirement_etherpad/__manifest__.py
odoo/addons/business_requirement_etherpad/i18n/sl.po
odoo/addons/business_requirement_etherpad/models/__init__.py
odoo/addons/business_requirement_etherpad/models/business.py
odoo/addons/business_requirement_etherpad/static/img/bus_etherpad.png
odoo/addons/business_requirement_etherpad/views/business_view.xml
odoo10_addon_business_requirement_etherpad-10.0.1.0.0.dist-info/DESCRIPTION.rst
odoo10_addon_business_requirement_etherpad-10.0.1.0.0.dist-info/METADATA
odoo10_addon_business_requirement_etherpad-10.0.1.0.0.dist-info/RECORD
odoo10_addon_business_requirement_etherpad-10.0.1.0.0.dist-info/WHEEL
odoo10_addon_business_requirement_etherpad-10.0.1.0.0.dist-info/metadata.json
odoo10_addon_business_requirement_etherpad-10.0.1.0.0.dist-info/namespace_packages.txt
odoo10_addon_business_requirement_etherpad-10.0.1.0.0.dist-info/top_level.txt
